stringx-0.7.5.dist-info/METADATA
stringx-0.7.5.dist-info/WHEEL
stringx-0.7.5.dist-info/licenses/LICENSE
stringx/__init__.py
stringx/client.py
stringx/py.typed
stringx-0.7.5.dist-info/RECORD
