Metadata-Version: 2.1
Name: stringx
Version: 0.7.5
Summary: STRING DB API Client
Keywords: string api client httpx sib cpr embl biodata elixir protein gene interaction
Author-Email: Hugo Cachitas <hcachitas@gmail.com>
License: MIT
Classifier: Development Status :: 4 - Beta
Classifier: Intended Audience :: Developers
Classifier: Intended Audience :: Education
Classifier: Intended Audience :: Healthcare Industry
Classifier: Intended Audience :: Science/Research
Classifier: Topic :: Software Development :: Build Tools
Classifier: License :: OSI Approved :: MIT License
Classifier: Programming Language :: Python :: 3
Classifier: Programming Language :: Python :: 3.9
Classifier: Programming Language :: Python :: 3.10
Classifier: Programming Language :: Python :: 3.11
Classifier: Programming Language :: Python :: 3.12
Classifier: Topic :: Scientific/Engineering
Classifier: Topic :: Scientific/Engineering :: Bio-Informatics
Classifier: Typing :: Typed
Project-URL: Homepage, https://pypi.org/project/stringx
Project-URL: Repository, https://github.com/cachitas/stringx
Project-URL: Issues, https://github.com/cachitas/stringx/issues
Requires-Python: >=3.9
Requires-Dist: httpx>=0.27.0
